lanius
