Metadata-Version: 1.1
Name: lanius
Version: 0.1.1
Summary: Lanius Markdown Viewer
Home-page: https://github.com/TomCrypto/lanius
Author: Thomas BENETEAU
Author-email: thomas.beneteau@yahoo.fr
License: MIT
Keywords: markdown,terminal,viewer
Platform: UNKNOWN
Classifier: Operating System :: Unix
Classifier: Programming Language :: Python
Classifier: Programming Language :: Python :: 3
Classifier: Environment :: Console
Classifier: Topic :: Text Processing
Classifier: Topic :: Text Processing :: Markup
Classifier: Topic :: Text Processing :: Filters
Classifier: Topic :: Utilities
